{
  "branchName": "feature/extract-components-from-step",
  "encodedBranchName": "feature-extract-components-from-step",
  "timestamp": "1562599181",
  "buildNumber": "1442",
  "triggeredBy": "eggerschwiler",
  "pullRequestUrl": "",
  "buildUrl": "https://circleci.com/gh/scenarioo/scenarioo/1442",
  "warArtifact": "https://1442-10269178-gh.circle-artifacts.com/0/scenarioo.war",
  "warArtifactSha256": "eda7ddd74ed4d0912201ff14054748be80b1c0ff901a6c99acc8a87191de9fe5",
  "exampleDocuArtifact": "https://1442-10269178-gh.circle-artifacts.com/0/exampleScenariooDocu.zip",
  "exampleDocuArtifactSha256": "81d33b224f421f64197c50e915a9a3457adb00decaff617a975b2cb0f792bd47",
  "docuArtifacts": [
    {
      "url": "https://1442-10269178-gh.circle-artifacts.com/0/e2eScenariooDocu.zip",
      "sha256": "b1e4647acb67c76928983741b856c9fb57d6e2a637795a66183f36d5275ffc34",
      "build": "1442"
    }
  ]
}
