{
  "branchName": "master",
  "encodedBranchName": "master",
  "timestamp": "1562157193",
  "buildNumber": "1331",
  "triggeredBy": "eggerschwiler",
  "pullRequestUrl": "",
  "buildUrl": "https://circleci.com/gh/scenarioo/scenarioo/1331",
  "warArtifact": "https://1331-10269178-gh.circle-artifacts.com/0/scenarioo.war",
  "warArtifactSha256": "b4c55d7b844997c09382668fd4c5eac8878b2153080384d70c1b57fe93496a03",
  "exampleDocuArtifact": "https://1331-10269178-gh.circle-artifacts.com/0/exampleScenariooDocu.zip",
  "exampleDocuArtifactSha256": "e515ab85ce5623415bd3ad843586d431763c87516f9707f407327d03c6420ac4",
  "docuArtifacts": [
    {
      "url": "https://1331-10269178-gh.circle-artifacts.com/0/e2eScenariooDocu.zip",
      "sha256": "ae6fd655c5bcac0c1ef68c149402cff3cad96a6027219ce914692ecd2e4a9441",
      "build": "1331"
    },
    {
      "url": "https://305-10269178-gh.circle-artifacts.com/0/e2eScenariooDocu.zip",
      "sha256": "2aeb6a72ca48da0c38d2dd18473074c254231e02e0606e8b1becde5527620c00",
      "build": "305"
    }
  ]
}
